gitassist/__init__.py
gitassist/cli.py
gitassist-0.4.4.dist-info/METADATA
gitassist-0.4.4.dist-info/WHEEL
gitassist-0.4.4.dist-info/entry_points.txt
gitassist-0.4.4.dist-info/top_level.txt
gitassist-0.4.4.dist-info/RECORD
