Metadata-Version: 2.4
Name: gitassist
Version: 0.4.4
Summary: AI-powered Git helper
Author-email: Vijay Bala <contact@vijaybala.com>
License: MIT
Requires-Python: >=3.7
Requires-Dist: click
Requires-Dist: openai
Requires-Dist: gitpython
